<?xml version="1.0" encoding="UTF-8" standalone="no"?>
<!DOCTYPE log SYSTEM "logger.dtd">
<log>
<record>
  <date>2023-07-02T16:22:36.061002500Z</date>
  <millis>1688314956061</millis>
  <nanos>2500</nanos>
  <sequence>0</sequence>
  <logger>dz_2.task_2</logger>
  <level>INFO</level>
  <class>dz_2.task_2</class>
  <method>listSort</method>
  <thread>1</thread>
  <message>Sort Array</message>
</record>
<record>
  <date>2023-07-02T16:22:36.102610100Z</date>
  <millis>1688314956102</millis>
  <nanos>610100</nanos>
  <sequence>1</sequence>
  <logger>dz_2.task_2</logger>
  <level>INFO</level>
  <class>dz_2.task_2</class>
  <method>listSort</method>
  <thread>1</thread>
  <message>Итерация: 0; Массив: [2, 5, 1, -7, 3, 64, 0]
</message>
</record>
<record>
  <date>2023-07-02T16:22:36.102610100Z</date>
  <millis>1688314956102</millis>
  <nanos>610100</nanos>
  <sequence>2</sequence>
  <logger>dz_2.task_2</logger>
  <level>INFO</level>
  <class>dz_2.task_2</class>
  <method>listSort</method>
  <thread>1</thread>
  <message>Итерация: 1; Массив: [2, 1, -7, 3, 5, 0, 64]
</message>
</record>
<record>
  <date>2023-07-02T16:22:36.103617400Z</date>
  <millis>1688314956103</millis>
  <nanos>617400</nanos>
  <sequence>3</sequence>
  <logger>dz_2.task_2</logger>
  <level>INFO</level>
  <class>dz_2.task_2</class>
  <method>listSort</method>
  <thread>1</thread>
  <message>Итерация: 2; Массив: [1, -7, 2, 3, 0, 5, 64]
</message>
</record>
<record>
  <date>2023-07-02T16:22:36.104617900Z</date>
  <millis>1688314956104</millis>
  <nanos>617900</nanos>
  <sequence>4</sequence>
  <logger>dz_2.task_2</logger>
  <level>INFO</level>
  <class>dz_2.task_2</class>
  <method>listSort</method>
  <thread>1</thread>
  <message>Итерация: 3; Массив: [-7, 1, 2, 0, 3, 5, 64]
</message>
</record>
<record>
  <date>2023-07-02T16:22:36.104617900Z</date>
  <millis>1688314956104</millis>
  <nanos>617900</nanos>
  <sequence>5</sequence>
  <logger>dz_2.task_2</logger>
  <level>INFO</level>
  <class>dz_2.task_2</class>
  <method>listSort</method>
  <thread>1</thread>
  <message>Итерация: 4; Массив: [-7, 1, 0, 2, 3, 5, 64]
</message>
</record>
<record>
  <date>2023-07-02T16:22:36.104617900Z</date>
  <millis>1688314956104</millis>
  <nanos>617900</nanos>
  <sequence>6</sequence>
  <logger>dz_2.task_2</logger>
  <level>INFO</level>
  <class>dz_2.task_2</class>
  <method>listSort</method>
  <thread>1</thread>
  <message>Итерация: 5; Массив: [-7, 0, 1, 2, 3, 5, 64]
</message>
</record>
</log>
